pwq-0.1.0.dist-info/METADATA
pwq-0.1.0.dist-info/WHEEL
pwq-0.1.0.dist-info/entry_points.txt
pwq/__init__.py
pwq/main.py
pwq-0.1.0.dist-info/RECORD
