Metadata-Version: 2.1
Name: pwq
Version: 0.1.0
Summary: Default template for PDM package
Author-Email: Yanli <mail@yanli.one>
License: MIT
Requires-Python: >=3.10
Requires-Dist: pdm>=2.26.1
